{
	"Rust Settings": {
		"prefix": "settings-rust",
		"body": [
			"{",
				"\"rust.all_features\": true,",
				"\"rust-client.channel\": \"nightly\",",
				"\"rust-client.rls-name\": \"rls-preview\",",
				"\"rust-client.rlsPath\": \"/home/ahellwig/.cargo/bin/rls\",",
				"\"rust-client.rustupPath\": \"/home/ahellwig/.cargo/bin/rustup\",",
				"\"rust.build_on_save\": true,",
				"\"rust-client.updateOnStartup\": true,",
				"\"rust.unstable_features\": true",
			"}"
		],
		"description": "VS Code settings for rust"
	},
	"CPP and Latex Settings": {
		"prefix": "cpplatex",
		"body": [
			"{",
			"/* C and C++ */",
			"\"C_Cpp.clang_format_fallbackStyle\": \"Google\",",
			"\"C_Cpp.clang_format_style\": \"LLVM\",",
			"\"C_Cpp.default.cppStandard\": \"c++17\",",
			"\"[cpp]\": {",
			"\"editor.autoIndent\": true,",
			"\"editor.tabSize\": 2,",
			"\"editor.insertSpaces\": true,",
			"\"editor.formatOnSave\": true",
			"},",
			"\"clang.cxxflags\": [",
			"\"-Wall\",",
			"\"-std=c++17\",",
			"\"-g\",",
			"\"-glldb\"",
			"],",
			"\"clang.diagnostic.enable\": false,",
			"\"clang.completion.enable\": true,",
			"/* Latex */",
			"\"latex-workshop.latex.tools\": [",
			"{",
			"\"name\": \"latexmk\",",
			"\"command\": \"latexmk\",",
			"\"args\": [",
			"\"-synctex=1\",",
			"\"-interaction=nonstopmode\",",
			"\"-file-line-error\",",
			"\"-pdf\",",
			"\"%DOC%\"",
			"]",
			"},",
			"{",
			"\"name\": \"pdflatex\",",
			"\"command\": \"pdflatex\",",
			"\"args\": [",
			"\"-synctex=1\",",
			"\"-interaction=nonstopmode\",",
			"\"-file-line-error\",",
			"\"%DOC%\"",
			"]",
			"},",
			"{",
			"\"name\": \"bibtex\",",
			"\"command\": \"bibtex\",",
			"\"args\": [\"%DOCFILE%\"]",
			"}",
			"],",
			"\"latex-workshop.latex.outputDir\": \"${workspaceRoot}/doc/assigned\",",
			"\"latex-workshop.latex.recipes\": [",
			"{",
			"\"name\": \"latexmk\",",
			"\"tools\": [\"latexmk\"]",
			"},",
			"{",
			"\"name\": \"pdflatex -> bibtex -> pdflatex*2\",",
			"\"tools\": [\"pdflatex\", \"bibtex\", \"pdflatex\", \"pdflatex\"]",
			"}",
			"],",
			"\"latex-preview.command\": \"latexmk\",",
			"\"files.associations\": {",
			"\"array\": \"cpp\",",
			"\"atomic\": \"cpp\",",
			"\"*.tcc\": \"cpp\",",
			"\"cctype\": \"cpp\",",
			"\"chrono\": \"cpp\",",
			"\"cinttypes\": \"cpp\",",
			"\"clocale\": \"cpp\",",
			"\"cmath\": \"cpp\",",
			"\"cstdarg\": \"cpp\",",
			"\"cstddef\": \"cpp\",",
			"\"cstdint\": \"cpp\",",
			"\"cstdio\": \"cpp\",",
			"\"cstdlib\": \"cpp\",",
			"\"cstring\": \"cpp\",",
			"\"ctime\": \"cpp\",",
			"\"cwchar\": \"cpp\",",
			"\"cwctype\": \"cpp\",",
			"\"list\": \"cpp\",",
			"\"unordered_map\": \"cpp\",",
			"\"vector\": \"cpp\",",
			"\"exception\": \"cpp\",",
			"\"fstream\": \"cpp\",",
			"\"functional\": \"cpp\",",
			"\"initializer_list\": \"cpp\",",
			"\"iosfwd\": \"cpp\",",
			"\"iostream\": \"cpp\",",
			"\"istream\": \"cpp\",",
			"\"limits\": \"cpp\",",
			"\"memory\": \"cpp\",",
			"\"numeric\": \"cpp\",",
			"\"optional\": \"cpp\",",
			"\"ostream\": \"cpp\",",
			"\"ratio\": \"cpp\",",
			"\"sstream\": \"cpp\",",
			"\"stdexcept\": \"cpp\",",
			"\"streambuf\": \"cpp\",",
			"\"string_view\": \"cpp\",",
			"\"system_error\": \"cpp\",",
			"\"type_traits\": \"cpp\",",
			"\"tuple\": \"cpp\",",
			"\"typeinfo\": \"cpp\",",
			"\"utility\": \"cpp\",",
			"\"algorithm\": \"cpp\"",
			"},",
			"\"cSpell.words\": [",
			"\"wconversion\"",
			"]",
			"}"
]
	}
}